saylani46165db/__init__.py
saylani46165db/saylani.py
saylani46165db-0.1.dist-info/METADATA
saylani46165db-0.1.dist-info/WHEEL
saylani46165db-0.1.dist-info/top_level.txt
saylani46165db-0.1.dist-info/RECORD
