Metadata-Version: 2.1
Name: saylani46165db
Version: 0.1
Summary: This is the Saylani DB Package
Author: Shahzad Ahmed Khan
License: UNKNOWN
Platform: UNKNOWN
